novita_sandbox/__init__.py
novita_sandbox/code_interpreter/__init__.py
novita_sandbox/code_interpreter/charts.py
novita_sandbox/code_interpreter/code_interpreter_async.py
novita_sandbox/code_interpreter/code_interpreter_sync.py
novita_sandbox/code_interpreter/constants.py
novita_sandbox/code_interpreter/exceptions.py
novita_sandbox/code_interpreter/models.py
novita_sandbox/code_interpreter/tests/benchmarking.py
novita_sandbox/code_interpreter/tests/conftest.py
novita_sandbox/code_interpreter/tests/async/test_async_bash.py
novita_sandbox/code_interpreter/tests/async/test_async_basic.py
novita_sandbox/code_interpreter/tests/async/test_async_callbacks.py
novita_sandbox/code_interpreter/tests/async/test_async_custom_repr_object.py
novita_sandbox/code_interpreter/tests/async/test_async_data.py
novita_sandbox/code_interpreter/tests/async/test_async_default_kernels.py
novita_sandbox/code_interpreter/tests/async/test_async_display_data.py
novita_sandbox/code_interpreter/tests/async/test_async_execution_count.py
novita_sandbox/code_interpreter/tests/async/test_async_kernels.py
novita_sandbox/code_interpreter/tests/async/test_async_reconnect.py
novita_sandbox/code_interpreter/tests/async/test_async_statefulness.py
novita_sandbox/code_interpreter/tests/async/test_async_streaming.py
novita_sandbox/code_interpreter/tests/async/env_vars/test_bash.py
novita_sandbox/code_interpreter/tests/async/env_vars/test_java.py
novita_sandbox/code_interpreter/tests/async/env_vars/test_js.py
novita_sandbox/code_interpreter/tests/async/env_vars/test_python.py
novita_sandbox/code_interpreter/tests/async/env_vars/test_r.py
novita_sandbox/code_interpreter/tests/charts/test_bar.py
novita_sandbox/code_interpreter/tests/charts/test_box_and_whiskers.py
novita_sandbox/code_interpreter/tests/charts/test_json.py
novita_sandbox/code_interpreter/tests/charts/test_line.py
novita_sandbox/code_interpreter/tests/charts/test_log_chart.py
novita_sandbox/code_interpreter/tests/charts/test_pie.py
novita_sandbox-1.0.4.dist-info/METADATA
novita_sandbox-1.0.4.dist-info/WHEEL
novita_sandbox-1.0.4.dist-info/RECORD
