Metadata-Version: 2.4
Name: novita-sandbox
Version: 1.0.4
Summary: Novita Agent Sandbox SDK - Python library for Novita Agent Sandbox
Project-URL: Homepage, https://novita.ai
Project-URL: Documentation, https://novita.ai/docs/guides/sandbox-overview
Project-URL: Bug Tracker, https://novita.ai
Project-URL: Changelog, https://novita.ai/docs/changelog
Author-email: Novita <support@novita.ai>
Maintainer-email: Novita <support@novita.ai>
License: MIT
Keywords: Novita,agent,ai,code-interpreter,desktop-automation,sandbox,sdk
Classifier: Development Status :: 4 - Beta
Classifier: Intended Audience :: Developers
Classifier: License :: OSI Approved :: MIT License
Classifier: Operating System :: OS Independent
Classifier: Programming Language :: Python :: 3
Classifier: Programming Language :: Python :: 3.9
Classifier: Programming Language :: Python :: 3.10
Classifier: Programming Language :: Python :: 3.11
Classifier: Programming Language :: Python :: 3.12
Classifier: Topic :: Scientific/Engineering :: Artificial Intelligence
Classifier: Topic :: Software Development :: Libraries :: Python Modules
Classifier: Topic :: System :: Operating System
Requires-Python: >=3.9
Requires-Dist: attrs>=23.2.0
Requires-Dist: httpcore>=1.0.5
Requires-Dist: httpx<1.0.0,>=0.27.0
Requires-Dist: packaging>=24.1
Requires-Dist: protobuf>=5.26.1
Requires-Dist: python-dateutil>=2.8.2
Requires-Dist: typing-extensions>=4.1.0
Provides-Extra: all
Requires-Dist: matplotlib>=3.6.0; extra == 'all'
Requires-Dist: numpy>=1.21.0; extra == 'all'
Requires-Dist: opencv-python>=4.7.0; extra == 'all'
Requires-Dist: pandas>=1.5.0; extra == 'all'
Requires-Dist: pillow>=9.0.0; extra == 'all'
Requires-Dist: plotly>=5.0.0; extra == 'all'
Requires-Dist: pyautogui>=0.9.54; extra == 'all'
Requires-Dist: pynput>=1.7.6; extra == 'all'
Requires-Dist: python-dateutil>=2.8.2; extra == 'all'
